slem/__init__.py
slem/model.py
slem/py.typed
slem/super_learner.py
slem/utils.py
slem_learn-0.0.14.dist-info/LICENSE
slem_learn-0.0.14.dist-info/METADATA
slem_learn-0.0.14.dist-info/WHEEL
slem_learn-0.0.14.dist-info/top_level.txt
slem_learn-0.0.14.dist-info/RECORD
